packaide_client/__init__.py
packaide_client/sync.py
packaide_client-1.0.2.dist-info/METADATA
packaide_client-1.0.2.dist-info/WHEEL
packaide_client-1.0.2.dist-info/top_level.txt
packaide_client-1.0.2.dist-info/RECORD
