Metadata-Version: 2.1
Name: packaide_client
Version: 1.0.2
Project-URL: Homepage, https://github.com/PoorRican/packaide_client
Project-URL: Repository, https://github.com/PoorRican/packaide_client
Project-URL: Issues, https://github.com/PoorRican/packaide_client/issues
Requires-Python: >=3.7
Requires-Dist: pydantic
Requires-Dist: requests
